dekshell-0.2.62.dist-info/METADATA
dekshell-0.2.62.dist-info/WHEEL
dekshell-0.2.62.dist-info/entry_points.txt
dekshell/__init__.py
dekshell/click/__entry__.py
dekshell/click/__init__.py
dekshell/core/__init__.py
dekshell/core/contexts/__init__.py
dekshell/core/contexts/methods.py
dekshell/core/contexts/properties.py
dekshell/core/markers/__init__.py
dekshell/core/markers/base/__init__.py
dekshell/core/markers/base/core.py
dekshell/core/markers/base/shell.py
dekshell/core/markers/commands.py
dekshell/core/markers/comment.py
dekshell/core/markers/define.py
dekshell/core/markers/echo.py
dekshell/core/markers/empty.py
dekshell/core/markers/env.py
dekshell/core/markers/exec.py
dekshell/core/markers/for_.py
dekshell/core/markers/function.py
dekshell/core/markers/if_.py
dekshell/core/markers/input.py
dekshell/core/markers/invoke.py
dekshell/core/markers/pip_.py
dekshell/core/markers/redirect.py
dekshell/core/markers/shell.py
dekshell/core/markers/var.py
dekshell/core/markers/while_.py
dekshell/core/plugin/__init__.py
dekshell/core/redirect.py
dekshell/utils/__init__.py
dekshell/utils/beep.py
dekshell/utils/cmd.py
dekshell/utils/pkg.py
dekshell/utils/serializer.py
dekshell/utils/shell.py
dekshell-0.2.62.dist-info/RECORD
