Metadata-Version: 2.1
Name: dekshell
Version: 0.2.62
Author-Email: sanzenwin <sanzenwin@gmail.com>
License: MIT
Requires-Python: >=3.7
Requires-Dist: packaging<=23.1
Requires-Dist: extra-platforms<=3.1.0
Requires-Dist: dektools[date,fetch,ignore,ps,tab]<1.0.0
Requires-Dist: dekmedia[audio]<1.0.0
